galah/ALA_keys.json
galah/Countries_Downloaded_In_21July2023.xlsx
galah/__init__.py
galah/apply_data_profile.py
galah/atlas_citation.py
galah/atlas_counts.py
galah/atlas_media.py
galah/atlas_occurrences.py
galah/atlas_species.py
galah/atlas_taxonomy.py
galah/common_dictionaries.py
galah/common_functions.py
galah/config.ini
galah/config.ini.default
galah/galah_config.py
galah/galah_filter.py
galah/galah_gbif_filters.py
galah/galah_geolocate.py
galah/galah_group_by.py
galah/galah_select.py
galah/gbif_assertions.csv
galah/gbif_fields.csv
galah/generate_jwt_token.py
galah/get_api_url.py
galah/node_config.csv
galah/node_config_0.1.0.csv
galah/node_config_R.csv
galah/node_config_dest.csv
galah/node_config_dev.csv
galah/node_config_full.csv
galah/node_config_old.csv
galah/search_all.py
galah/search_taxa.py
galah/search_values.py
galah/show_all.py
galah/show_values.py
galah/version.py
galah/.idea/.gitignore
galah/.idea/galah.iml
galah/.idea/misc.xml
galah/.idea/modules.xml
galah/.idea/vcs.xml
galah/.idea/inspectionProfiles/profiles_settings.xml
galah/__pycache__/__init__.cpython-311.pyc
galah/__pycache__/apply_data_profile.cpython-311.pyc
galah/__pycache__/atlas_counts.cpython-311.pyc
galah/__pycache__/atlas_media.cpython-311.pyc
galah/__pycache__/atlas_occurrences.cpython-311.pyc
galah/__pycache__/atlas_species.cpython-311.pyc
galah/__pycache__/common_dictionaries.cpython-311.pyc
galah/__pycache__/common_functions.cpython-311.pyc
galah/__pycache__/galah_config.cpython-311.pyc
galah/__pycache__/galah_filter.cpython-311.pyc
galah/__pycache__/galah_geolocate.cpython-311.pyc
galah/__pycache__/galah_group_by.cpython-311.pyc
galah/__pycache__/galah_select.cpython-311.pyc
galah/__pycache__/generate_jwt_token.cpython-311.pyc
galah/__pycache__/get_api_url.cpython-311.pyc
galah/__pycache__/search_all.cpython-311.pyc
galah/__pycache__/search_taxa.cpython-311.pyc
galah/__pycache__/search_values.cpython-311.pyc
galah/__pycache__/show_all.cpython-311.pyc
galah_python-0.12.1.dist-info/METADATA
galah_python-0.12.1.dist-info/WHEEL
galah_python-0.12.1.dist-info/top_level.txt
galah_python-0.12.1.dist-info/RECORD
