Metadata-Version: 2.4
Name: galah-python
Version: 0.12.1
Summary: Get counts and information on species from many different atlases
Home-page: https://galah.ala.org.au/Python/
Author: Amanda Buyan
Author-email: amanda.buyan@csiro.au
License: MPL-2.0
Keywords: galah
Requires-Dist: setuptools
Requires-Dist: numpy
Requires-Dist: pandas
Requires-Dist: requests
Requires-Dist: urllib3
Requires-Dist: zip-files
Requires-Dist: configparser
Requires-Dist: glob2
Requires-Dist: bytesbufio
Requires-Dist: shutils
Requires-Dist: pytest
Requires-Dist: unittest2py3k
Requires-Dist: shapely
Requires-Dist: geopandas
Requires-Dist: tqdm
Dynamic: author
Dynamic: author-email
Dynamic: description
Dynamic: description-content-type
Dynamic: home-page
Dynamic: keywords
Dynamic: license
Dynamic: requires-dist
Dynamic: summary
